odoo/addons/hr_employee_firstname_partner_firstname/README.rst
odoo/addons/hr_employee_firstname_partner_firstname/__init__.py
odoo/addons/hr_employee_firstname_partner_firstname/__manifest__.py
odoo/addons/hr_employee_firstname_partner_firstname/i18n/fr.po
odoo/addons/hr_employee_firstname_partner_firstname/i18n/hr_employee_firstname_partner_firstname.pot
odoo/addons/hr_employee_firstname_partner_firstname/i18n/it.po
odoo/addons/hr_employee_firstname_partner_firstname/models/__init__.py
odoo/addons/hr_employee_firstname_partner_firstname/models/hr_employee.py
odoo/addons/hr_employee_firstname_partner_firstname/readme/CONTRIBUTORS.rst
odoo/addons/hr_employee_firstname_partner_firstname/readme/DESCRIPTION.rst
odoo/addons/hr_employee_firstname_partner_firstname/static/description/icon.png
odoo/addons/hr_employee_firstname_partner_firstname/static/description/index.html
odoo/addons/hr_employee_firstname_partner_firstname/tests/__init__.py
odoo/addons/hr_employee_firstname_partner_firstname/tests/test_module.py
odoo_addon_hr_employee_firstname_partner_firstname-16.0.1.0.0.4.dist-info/METADATA
odoo_addon_hr_employee_firstname_partner_firstname-16.0.1.0.0.4.dist-info/WHEEL
odoo_addon_hr_employee_firstname_partner_firstname-16.0.1.0.0.4.dist-info/top_level.txt
odoo_addon_hr_employee_firstname_partner_firstname-16.0.1.0.0.4.dist-info/RECORD
