Metadata-Version: 2.1
Name: odoo-addon-hr_employee_firstname_partner_firstname
Version: 16.0.1.0.0.4
Summary: Glue module between partner_firstname and hr_employee_firstname
Home-page: https://github.com/OCA/hr
Author: GRAP, Odoo Community Association (OCA)
Author-email: support@odoo-community.org
License: AGPL-3
Classifier: Programming Language :: Python
Classifier: Framework :: Odoo
Classifier: Framework :: Odoo :: 16.0
Classifier: License :: OSI Approved :: GNU Affero General Public License v3
Requires-Python: >=3.10
Requires-Dist: odoo-addon-hr-employee-firstname<16.1dev,>=16.0dev
Requires-Dist: odoo-addon-partner-firstname<16.1dev,>=16.0dev
Requires-Dist: odoo<16.1dev,>=16.0a
